namespaces.cpython-310-aarch64-linux-gnu.so
namespaces.py-1.0.1.dist-info/RECORD
namespaces.py-1.0.1.dist-info/top_level.txt
namespaces.py-1.0.1.dist-info/LICENSE
namespaces.py-1.0.1.dist-info/WHEEL
namespaces.py-1.0.1.dist-info/METADATA
