Metadata-Version: 2.1
Name: namespaces.py
Version: 1.0.1
Summary: No more stupid dots.
Author-email: ZeroIntensity <zintensitydev@gmail.com>
License: MIT
Project-URL: Source, https://github.com/ZeroIntensity/namespaces.py
Requires-Python: >=3.7
License-File: LICENSE
